[{"id":65,"birthDate":"2005-09-08T07:00:00.000Z","currentTemple":"恆德佛堂","gender":"乾","age":17,"name":"Brandon Kuang","taoClasses":{"xingMing":{"completionDate":"2022-04-30T07:00:00.000Z","completed":true},"zhiShan":{"completed":false},"peiDe":{"completed":false},"xingDe":{"completed":false},"chongDe":{"completed":false},"lecturer":{"completed":false}},"vows":{"holyOverWorldlyAffair":{"made":true,"dateMade":"2021-08-22T07:00:00.000Z"},"shareWealthAndTruth":{"made":true,"dateMade":"2021-08-22T07:00:00.000Z"}}},{"id":73,"birthDate":"2005-03-25T08:00:00.000Z","gender":"乾","age":17,"name":"Johnny Zhong Liang","taoClasses":{"xingMing":{"completed":true,"completionDate":"2022-04-30T07:00:00.000Z"},"zhiShan":{"completed":false},"peiDe":{"completed":false},"xingDe":{"completed":false},"chongDe":{"completed":false},"lecturer":{"completed":false}},"altName":"梁志忠","vows":{"holyOverWorldlyAffair":{"dateMade":"2021-08-22T07:00:00.000Z","made":true},"shareWealthAndTruth":{"dateMade":"2021-08-22T07:00:00.000Z","made":true}},"currentTemple":"恆德壇"},{"id":75,"birthDate":"2000-09-29T07:00:00.000Z","currentTemple":"恆德佛堂","gender":"坤","age":22,"name":"梁倩儀","taoClasses":{"xingMing":{"completed":true,"completionDate":"2017-05-13T16:00:00.000Z"},"zhiShan":{"completed":true,"completionDate":"2019-12-31T08:00:00.000Z"},"peiDe":{"completed":false},"xingDe":{"completed":false},"chongDe":{"completed":false},"lecturer":{"completed":false}},"altName":"Sandy Liang","vows":{"holyOverWorldlyAffair":{"dateMade":"2017-03-05T08:00:00.000Z","made":true},"shareWealthAndTruth":{"dateMade":"2017-03-05T08:00:00.000Z","made":true},"taoHelper":{"dateMade":"2017-05-13T16:00:00.000Z","made":true}}},{"id":83,"birthDate":"1984-01-01T08:00:00.000Z","currentTemple":"恆德壇","gender":"坤","age":38,"name":"吳潤瓊","taoClasses":{"lecturer":{"completed":false},"xingDe":{"completed":true,"completionDate":"2017-05-13T16:00:00.000Z"},"peiDe":{"completed":false},"zhiShan":{"completed":false},"xingMing":{"completionDate":"2013-01-01T08:00:00.000Z","completed":true},"chongDe":{"completed":true,"completionDate":"2021-05-09T07:00:00.000Z"}},"vows":{"assistantLecturer":{"made":true,"dateMade":"2016-06-12T07:00:00.000Z"},"taoHelper":{"dateMade":"2013-09-22T07:00:00.000Z","made":true},"assistantTempleHost":{"dateMade":"2017-05-13T16:00:00.000Z","made":true},"templeHost":{},"lecturer":{},"transmittingMaster":{},"plantTaoSeed":{},"devoteToTaoPropagation":{},"establishTemple":{},"vegetarian":{"dateMade":"2019-07-28T07:00:00.000Z","made":true},"shareWealthAndTruth":{},"holyOverWorldlyAffair":{}}},{"id":145,"birthDate":"1984-01-01T08:00:00.000Z","gender":"坤","age":38,"name":"胡艷蘭","taoClasses":{"lecturer":{"completed":false},"xingDe":{"completed":true,"completionDate":"2018-12-09T08:00:00.000Z"},"peiDe":{"completed":true,"completionDate":"2019-11-30T08:00:00.000Z"},"zhiShan":{"completed":false},"xingMing":{"completed":true,"completionDate":"2017-05-13T16:00:00.000Z"}},"vows":{"vegetarian":{"dateMade":"2021-07-25T07:00:00.000Z","made":true},"assistantTempleHost":{"dateMade":"2019-05-12T07:00:00.000Z","made":true},"taoHelper":{"dateMade":"2017-05-13T16:00:00.000Z","made":true}},"currentTemple":"沾德壇"},{"age":60,"birthDate":"1962-04-08T07:00:00.000Z","currentTemple":"同德壇","gender":"乾","id":209,"name":"蕭茂達","taoClasses":{"xingMing":{"completed":false},"zhiShan":{"completed":false},"peiDe":{"completed":true,"completionDate":"2012-01-01T08:00:00.000Z"},"xingDe":{"completed":true,"completionDate":"2013-01-01T08:00:00.000Z"},"lecturer":{"completed":false}},"vows":{"assistantLecturer":{"dateMade":"2011-11-06T07:00:00.000Z","made":true},"vegetarian":{"dateMade":"2015-04-26T07:00:00.000Z"},"lecturer":{"dateMade":"2015-04-26T07:00:00.000Z","made":true},"templeHost":{"dateMade":"2011-11-06T07:00:00.000Z","made":true},"taoHelper":{"made":true,"dateMade":"2010-11-07T07:00:00.000Z"},"assistantTempleHost":{"made":true,"dateMade":"2010-11-07T07:00:00.000Z"}},"altName":"Victor Quoc Tieu"},{"id":279,"birthDate":"1959-01-01T08:00:00.000Z","currentTemple":"同德壇","gender":"坤","age":63,"name":"楊艷玲","taoClasses":{"xingMing":{"completed":false},"zhiShan":{"completed":false},"peiDe":{"completed":false},"xingDe":{"completed":false},"chongDe":{"completed":true,"completionDate":"2019-11-30T08:00:00.000Z"},"lecturer":{"completed":false}},"vows":{"assistantTempleHost":{"dateMade":"2019-05-12T07:00:00.000Z","made":true},"taoHelper":{"dateMade":"2010-11-07T07:00:00.000Z","made":true},"assistantLecturer":{"made":true,"dateMade":"2011-11-06T07:00:00.000Z"}}},{"id":288,"birthDate":"1964-01-01T08:00:00.000Z","gender":"坤","age":58,"name":"李鳳玲","taoClasses":{"lecturer":{"completed":false},"xingDe":{"completed":true},"peiDe":{"completionDate":"2012-01-01T08:00:00.000Z","completed":true},"zhiShan":{"completed":true},"xingMing":{"completed":true},"chongDe":{"completed":true,"completionDate":"2019-11-30T08:00:00.000Z"}},"vows":{"assistantLecturer":{"made":true,"dateMade":"2011-11-06T07:00:00.000Z"},"taoHelper":{"dateMade":"2010-11-07T07:00:00.000Z","made":true},"assistantTempleHost":{"dateMade":"2010-11-07T07:00:00.000Z","made":true},"templeHost":{"made":true,"dateMade":"2011-11-06T07:00:00.000Z"},"lecturer":{},"transmittingMaster":{},"plantTaoSeed":{},"devoteToTaoPropagation":{},"establishTemple":{},"vegetarian":{"made":true,"dateMade":"2015-04-26T07:00:00.000Z"},"shareWealthAndTruth":{},"holyOverWorldlyAffair":{}},"currentTemple":"同德壇"},{"id":328,"birthDate":"1956-01-01T08:00:00.000Z","currentTemple":"同德佛堂","gender":"乾","age":66,"name":"李進健","taoClasses":{"xingMing":{"completed":true,"completionDate":"2017-05-13T16:00:00.000Z"},"zhiShan":{"completed":true,"completionDate":"2019-11-30T08:00:00.000Z"},"peiDe":{"completionDate":"2021-01-01T08:00:00.000Z","completed":true},"xingDe":{"completed":false},"chongDe":{"completed":false},"lecturer":{"completed":false}},"vows":{"vegetarian":{"made":true,"dateMade":"2020-08-30T07:00:00.000Z"},"taoHelper":{"made":true,"dateMade":"2019-05-12T07:00:00.000Z"}}},{"id":347,"birthDate":"1956-01-01T08:00:00.000Z","gender":"坤","age":66,"name":"江桂明","taoClasses":{"xingMing":{"completed":false},"zhiShan":{"completed":true,"completionDate":"2013-01-01T08:00:00.000Z"},"peiDe":{"completed":true,"completionDate":"2012-01-01T08:00:00.000Z"},"xingDe":{"completed":true,"completionDate":"2018-12-09T08:00:00.000Z"},"chongDe":{"completed":true,"completionDate":"2019-11-30T08:00:00.000Z"},"lecturer":{"completed":false}},"vows":{"assistantLecturer":{"dateMade":"2013-09-22T07:00:00.000Z","made":true},"templeHost":{"made":true}},"currentTemple":"同德壇"},{"id":350,"birthDate":"2005-05-20T07:00:00.000Z","gender":"乾","age":17,"name":"Aaron H Chen","taoClasses":{"lecturer":{"completed":false},"chongDe":{"completed":false},"xingDe":{"completed":false},"peiDe":{"completed":false},"zhiShan":{"completed":false},"xingMing":{"completed":true,"completionDate":"2022-04-30T07:00:00.000Z"}},"altName":"黄宇","vows":{"shareWealthAndTruth":{"made":true,"dateMade":"2021-08-22T07:00:00.000Z"},"holyOverWorldlyAffair":{"made":true,"dateMade":"2021-08-22T07:00:00.000Z"}},"currentTemple":"沾德壇"},{"id":460,"birthDate":"1948-01-01T08:00:00.000Z","currentTemple":"恆德佛堂","gender":"坤","age":74,"name":"李玉英","taoClasses":{"xingMing":{"completed":false},"zhiShan":{"completed":true,"completionDate":"2018-12-09T08:00:00.000Z"},"peiDe":{"completed":true,"completionDate":"2019-11-30T08:00:00.000Z"},"xingDe":{"completionDate":"2022-02-27T08:00:00.000Z","completed":true},"chongDe":{"completed":false},"lecturer":{"completed":false}},"vows":{"assistantLecturer":{"dateMade":"2019-05-12T07:00:00.000Z","made":true}}},{"id":465,"birthDate":"2004-07-07T07:00:00.000Z","gender":"乾","age":18,"name":"Tommy Chen","taoClasses":{"lecturer":{"completed":false},"chongDe":{"completed":false},"xingDe":{"completed":false},"peiDe":{"completed":false},"zhiShan":{"completed":false},"xingMing":{"completed":true,"completionDate":"2021-06-19T07:00:00.000Z"}},"altName":"陳華濱","vows":{"shareWealthAndTruth":{"made":true,"dateMade":"2019-11-03T08:00:00.000Z"},"holyOverWorldlyAffair":{"made":true,"dateMade":"2019-11-03T08:00:00.000Z"}},"currentTemple":"恆德壇"},{"id":535,"birthDate":"1975-01-01T08:00:00.000Z","currentTemple":"恆德佛堂","gender":"坤","age":47,"name":"黃燕川","taoClasses":{"chongDe":{"completionDate":"2021-05-09T07:00:00.000Z","completed":true},"lecturer":{"completed":false},"xingDe":{"completionDate":"2012-01-01T08:00:00.000Z","completed":true},"peiDe":{"completed":false},"zhiShan":{"completed":false},"xingMing":{"completed":false}},"vows":{"assistantLecturer":{"dateMade":"2010-11-07T07:00:00.000Z","made":true},"taoHelper":{"made":true,"dateMade":"2009-10-01T07:00:00.000Z"}}},{"gender":"坤","id":649,"name":"廖淑美","taoClasses":{"lecturer":{"completed":false},"xingDe":{"completionDate":"2012-01-01T08:00:00.000Z","completed":true},"peiDe":{"completed":false},"zhiShan":{"completed":false},"xingMing":{"completed":false}},"vows":{"assistantLecturer":{"made":true,"dateMade":"2010-11-07T07:00:00.000Z"},"taoHelper":{"dateMade":"2003-08-20T07:00:00.000Z","made":true},"assistantTempleHost":{"made":true,"dateMade":"2010-11-07T07:00:00.000Z"},"templeHost":{"made":true,"dateMade":"2013-09-22T07:00:00.000Z"},"lecturer":{"made":true},"transmittingMaster":{},"plantTaoSeed":{},"devoteToTaoPropagation":{},"establishTemple":{},"vegetarian":{"made":true,"dateMade":"2013-09-22T07:00:00.000Z"},"shareWealthAndTruth":{},"holyOverWorldlyAffair":{}},"birthDate":"1950-01-01T08:00:00.000Z","age":72,"currentTemple":"同德壇"},{"id":792,"gender":"乾","name":"蘇國偉","taoClasses":{"lecturer":{"completed":false},"chongDe":{"completionDate":"2021-05-09T07:00:00.000Z","completed":true},"xingDe":{"completionDate":"2017-05-13T16:00:00.000Z","completed":true},"peiDe":{"completed":false},"zhiShan":{"completed":false},"xingMing":{"completed":false}},"currentTemple":"正德壇","vows":{"assistantTempleHost":{"made":true,"dateMade":"2018-05-13T07:00:00.000Z"}}},{"id":793,"currentTemple":"沾德壇","gender":"乾","name":"Frank Kellum","taoClasses":{"xingMing":{"completionDate":"2021-05-09T07:00:00.000Z","completed":true},"zhiShan":{"completed":true,"completionDate":"2022-01-23T08:00:00.000Z"},"peiDe":{"completed":false},"xingDe":{"completed":false},"lecturer":{"completed":false}}},{"id":852,"birthDate":"1960-01-01T08:00:00.000Z","gender":"坤","age":62,"name":"伍杏娜","taoClasses":{"xingMing":{"completed":true,"completionDate":"2012-01-01T08:00:00.000Z"},"zhiShan":{"completed":true,"completionDate":"2021-05-09T07:00:00.000Z"},"peiDe":{"completionDate":"2022-01-23T08:00:00.000Z","completed":true},"xingDe":{"completed":false},"lecturer":{"completed":false}},"vows":{"holyOverWorldlyAffair":{},"shareWealthAndTruth":{},"vegetarian":{},"establishTemple":{},"devoteToTaoPropagation":{},"plantTaoSeed":{},"transmittingMaster":{},"lecturer":{},"templeHost":{},"assistantTempleHost":{"dateMade":"2012-11-04T07:00:00.000Z","made":true},"taoHelper":{"dateMade":"2012-11-04T07:00:00.000Z","made":true},"assistantLecturer":{}},"currentTemple":"沾德壇"},{"id":883,"birthDate":"1975-01-01T08:00:00.000Z","gender":"坤","age":47,"name":"張堅萍","taoClasses":{"lecturer":{"completed":false},"chongDe":{"completed":false},"xingDe":{"completed":false},"peiDe":{"completed":false},"zhiShan":{"completionDate":"2022-01-23T08:00:00.000Z","completed":true},"xingMing":{"completed":true,"completionDate":"2021-05-09T07:00:00.000Z"}},"currentTemple":"沾德壇"},{"id":908,"gender":"乾","name":"潘德記","taoClasses":{"chongDe":{"completionDate":"2021-05-09T07:00:00.000Z","completed":true},"lecturer":{"completed":false},"xingDe":{"completed":false},"peiDe":{"completionDate":"2012-01-01T08:00:00.000Z","completed":true},"zhiShan":{"completed":false},"xingMing":{"completed":false}},"vows":{"assistantLecturer":{"dateMade":"2010-11-07T07:00:00.000Z","made":true},"taoHelper":{"made":true,"dateMade":"2009-10-01T07:00:00.000Z"},"assistantTempleHost":{"made":true,"dateMade":"2011-11-06T07:00:00.000Z"},"templeHost":{},"lecturer":{},"transmittingMaster":{},"plantTaoSeed":{},"devoteToTaoPropagation":{},"establishTemple":{},"vegetarian":{},"shareWealthAndTruth":{},"holyOverWorldlyAffair":{}},"currentTemple":"沾德壇"},{"id":938,"gender":"坤","name":"黃韻瑞","taoClasses":{"xingMing":{"completed":false},"zhiShan":{"completionDate":"2018-05-13T07:00:00.000Z","completed":false},"peiDe":{"completed":true,"completionDate":"2018-12-09T08:00:00.000Z"},"xingDe":{"completed":false},"chongDe":{"completed":false},"lecturer":{"completed":false}},"birthDate":"1992-03-28T08:00:00.000Z","altName":"Victoria Huang","currentTemple":"同德壇","age":30,"vows":{"vegetarian":{"dateMade":"2019-05-12T07:00:00.000Z","made":true},"templeHost":{"dateMade":"2019-05-12T07:00:00.000Z","made":true},"taoHelper":{"dateMade":"2018-05-13T07:00:00.000Z","made":true},"assistantLecturer":{"dateMade":"2019-05-12T07:00:00.000Z","made":true}}},{"id":939,"gender":"坤","name":"黃韻恆","altName":"Lisa Huang","taoClasses":{"lecturer":{"completed":false},"xingDe":{"completed":false},"peiDe":{"completed":false},"zhiShan":{"completed":false},"xingMing":{"completed":false}},"vows":{"holyOverWorldlyAffair":{"dateMade":"2008-10-25T07:00:00.000Z","made":true},"shareWealthAndTruth":{"dateMade":"2008-10-25T07:00:00.000Z","made":true},"vegetarian":{"dateMade":"2008-10-25T07:00:00.000Z","made":true},"establishTemple":{},"devoteToTaoPropagation":{},"plantTaoSeed":{},"transmittingMaster":{},"lecturer":{"dateMade":"2008-10-25T07:00:00.000Z","made":true},"templeHost":{"dateMade":"2006-03-19T07:00:00.000Z","made":true},"assistantTempleHost":{},"taoHelper":{"dateMade":"2000-10-04T07:00:00.000Z","made":true},"assistantLecturer":{"made":true,"dateMade":"2003-08-20T07:00:00.000Z"}},"currentTemple":"同德壇","birthDate":"1983-01-01T08:00:00.000Z","age":39},{"age":36,"altName":"Alice Huang","birthDate":"1986-09-15T07:00:00.000Z","currentTemple":"同德壇","gender":"坤","id":940,"name":"黃韻如","taoClasses":{"lecturer":{"completed":false},"xingDe":{"completed":false},"peiDe":{"completed":false},"zhiShan":{"completed":false},"xingMing":{"completed":false}},"vows":{"assistantLecturer":{"dateMade":"2010-11-07T07:00:00.000Z","made":true},"taoHelper":{"made":true,"dateMade":"2003-08-20T07:00:00.000Z"},"assistantTempleHost":{"made":true,"dateMade":"2006-03-19T07:00:00.000Z"},"templeHost":{"made":true,"dateMade":"2011-11-06T07:00:00.000Z"},"lecturer":{"made":true,"dateMade":"2015-04-26T07:00:00.000Z"},"transmittingMaster":{},"plantTaoSeed":{},"devoteToTaoPropagation":{},"establishTemple":{},"vegetarian":{"made":true,"dateMade":"2015-04-26T07:00:00.000Z"},"shareWealthAndTruth":{},"holyOverWorldlyAffair":{}}},{"id":948,"gender":"坤","name":"潘婉玲","taoClasses":{"lecturer":{"completed":false},"chongDe":{"completionDate":"2021-05-09T07:00:00.000Z","completed":true},"xingDe":{"completionDate":"2017-05-13T16:00:00.000Z","completed":true},"peiDe":{"completed":false},"zhiShan":{"completed":false},"xingMing":{"completed":false}},"currentTemple":"正德壇","vows":{"assistantTempleHost":{"made":true,"dateMade":"2018-05-13T07:00:00.000Z"}}},{"id":968,"gender":"坤","name":"林輝","taoClasses":{"xingMing":{"completed":true,"completionDate":"2021-05-09T07:00:00.000Z"},"zhiShan":{"completed":true,"completionDate":"2022-01-23T08:00:00.000Z"},"peiDe":{"completed":false},"xingDe":{"completed":false},"chongDe":{"completed":false},"lecturer":{"completed":false}},"currentTemple":"明德壇"},{"id":991,"gender":"乾","name":"孫學健","taoClasses":{"xingMing":{"completed":false},"zhiShan":{"completed":false},"peiDe":{"completed":false},"xingDe":{"completed":false},"lecturer":{"completed":false}},"vows":{"assistantLecturer":{"made":true,"dateMade":"2000-10-04T07:00:00.000Z"},"taoHelper":{"dateMade":"1998-09-06T07:00:00.000Z","made":true},"assistantTempleHost":{"made":false},"templeHost":{"made":true,"dateMade":"1999-10-16T07:00:00.000Z"},"lecturer":{"dateMade":"2003-08-20T07:00:00.000Z","made":true},"transmittingMaster":{},"plantTaoSeed":{},"devoteToTaoPropagation":{},"establishTemple":{},"vegetarian":{},"shareWealthAndTruth":{},"holyOverWorldlyAffair":{}},"currentTemple":"同德壇"},{"id":992,"name":"周宏逵","taoClasses":{"xingMing":{"completed":false},"zhiShan":{"completed":false},"peiDe":{"completed":false},"xingDe":{"completed":false},"lecturer":{"completed":false}},"vows":{"holyOverWorldlyAffair":{},"shareWealthAndTruth":{},"vegetarian":{},"establishTemple":{},"devoteToTaoPropagation":{},"plantTaoSeed":{},"transmittingMaster":{},"lecturer":{"made":true},"templeHost":{"made":true},"assistantTempleHost":{},"taoHelper":{},"assistantLecturer":{}},"gender":"乾","currentTemple":"正德壇"},{"id":993,"currentTemple":"沾德壇","name":"周宏菁","altName":"Cheryl","taoClasses":{"xingMing":{"completed":false},"zhiShan":{"completed":false},"peiDe":{"completed":false},"xingDe":{"completed":false},"lecturer":{"completed":false}},"vows":{"holyOverWorldlyAffair":{},"shareWealthAndTruth":{},"vegetarian":{},"establishTemple":{},"devoteToTaoPropagation":{},"plantTaoSeed":{},"transmittingMaster":{},"lecturer":{"dateMade":"2006-03-19T07:00:00.000Z","made":true},"templeHost":{"made":true,"dateMade":"2000-10-04T07:00:00.000Z"},"assistantTempleHost":{},"taoHelper":{"dateMade":"2000-10-04T07:00:00.000Z","made":true},"assistantLecturer":{}},"gender":"坤","birthDate":"1959-01-01T08:00:00.000Z","age":63},{"id":998,"name":"王彥元","taoClasses":{"lecturer":{"completed":false},"chongDe":{"completed":false},"xingDe":{"completed":false},"peiDe":{"completed":false},"zhiShan":{"completed":false},"xingMing":{"completed":false}},"gender":"坤","birthDate":"1976-01-01T08:00:00.000Z","age":46,"vows":{"templeHost":{"made":true,"dateMade":"2018-05-13T07:00:00.000Z"},"lecturer":{"made":true,"dateMade":"2011-11-06T07:00:00.000Z"},"vegetarian":{"made":true,"dateMade":"2018-05-13T07:00:00.000Z"}},"currentTemple":"丞德壇","altName":"Debbie Wang"},{"id":1018,"name":"沈宮芳","taoClasses":{"lecturer":{"completed":false},"xingDe":{"completed":false},"peiDe":{"completed":false},"zhiShan":{"completed":false},"xingMing":{"completed":false}},"vows":{"assistantLecturer":{"made":true,"dateMade":"2000-10-04T07:00:00.000Z"},"taoHelper":{},"assistantTempleHost":{},"templeHost":{"dateMade":"2000-10-04T07:00:00.000Z","made":true},"lecturer":{"dateMade":"2003-08-20T07:00:00.000Z","made":true},"transmittingMaster":{},"plantTaoSeed":{},"devoteToTaoPropagation":{},"establishTemple":{},"vegetarian":{},"shareWealthAndTruth":{},"holyOverWorldlyAffair":{}},"gender":"坤","birthDate":"1958-01-01T08:00:00.000Z","age":64,"currentTemple":"同德壇"},{"id":1028,"name":"夏樹寧","taoClasses":{"lecturer":{"completed":false},"chongDe":{"completed":false},"xingDe":{"completed":false},"peiDe":{"completed":false},"zhiShan":{"completed":false},"xingMing":{"completed":false}},"vows":{"assistantTempleHost":{"dateMade":"1998-09-06T07:00:00.000Z","made":true},"templeHost":{"made":true},"lecturer":{"dateMade":"2003-08-20T07:00:00.000Z","made":true},"assistantLecturer":{"made":true,"dateMade":"2000-10-04T07:00:00.000Z"}},"gender":"坤","currentTemple":"同德壇"},{"id":1029,"birthDate":"1954-01-01T08:00:00.000Z","gender":"坤","age":68,"name":"萬慧敏","taoClasses":{"chongDe":{"completionDate":"2019-11-30T08:00:00.000Z","completed":true},"xingMing":{"completed":false},"zhiShan":{"completed":false},"peiDe":{"completed":false},"xingDe":{"completionDate":"2018-12-09T08:00:00.000Z","completed":true},"lecturer":{"completed":false}},"vows":{"taoHelper":{"dateMade":"2009-10-01T07:00:00.000Z","made":true},"assistantTempleHost":{"made":true},"vegetarian":{"made":true,"dateMade":"2020-08-04T07:00:00.000Z"},"assistantLecturer":{"made":true,"dateMade":"2010-11-07T07:00:00.000Z"}},"currentTemple":"同德壇"},{"id":1032,"name":"雷秀珊","taoClasses":{"xingMing":{"completed":false},"zhiShan":{"completed":false},"peiDe":{"completed":false},"xingDe":{"completed":false},"lecturer":{"completed":false}},"vows":{"assistantLecturer":{},"taoHelper":{},"assistantTempleHost":{},"templeHost":{"made":true,"dateMade":"2006-03-19T07:00:00.000Z"},"lecturer":{"made":true,"dateMade":"2006-03-19T07:00:00.000Z"},"transmittingMaster":{},"plantTaoSeed":{},"devoteToTaoPropagation":{},"establishTemple":{},"vegetarian":{},"shareWealthAndTruth":{},"holyOverWorldlyAffair":{}},"gender":"坤","currentTemple":"同德壇","birthDate":"1948-01-01T08:00:00.000Z","age":74},{"id":1047,"name":"夏樹華","taoClasses":{"lecturer":{"completed":false},"xingDe":{"completed":false},"peiDe":{"completed":true},"zhiShan":{"completed":true},"xingMing":{"completed":true}},"gender":"坤","vows":{"assistantLecturer":{"made":true},"taoHelper":{"made":true},"templeHost":{"dateMade":"1998-09-06T07:00:00.000Z","made":true},"lecturer":{"dateMade":"1998-09-06T07:00:00.000Z","made":true},"transmittingMaster":{"dateMade":"2013-07-24T07:00:00.000Z","made":true},"plantTaoSeed":{"dateMade":"2013-07-24T07:00:00.000Z","made":true},"devoteToTaoPropagation":{"dateMade":"2013-07-24T07:00:00.000Z","made":true},"establishTemple":{"dateMade":"1996-09-15T07:00:00.000Z","made":true},"vegetarian":{"dateMade":"1997-01-01T08:00:00.000Z","made":true},"shareWealthAndTruth":{"dateMade":"1996-04-20T07:00:00.000Z","made":true},"holyOverWorldlyAffair":{"dateMade":"1996-04-20T07:00:00.000Z","made":true}},"birthDate":"1954-02-20T08:00:00.000Z","age":68,"currentTemple":"同德壇"},{"id":1155,"birthDate":"1977-01-01T08:00:00.000Z","gender":"坤","age":45,"name":"陳惠紅","altName":"Shirley Chen","taoClasses":{"chongDe":{"completionDate":"2022-01-23T08:00:00.000Z","completed":true},"lecturer":{"completed":false},"xingDe":{"completed":true,"completionDate":"2021-05-09T07:00:00.000Z"},"peiDe":{"completed":false},"zhiShan":{"completionDate":"2013-01-01T08:00:00.000Z","completed":true},"xingMing":{"completionDate":"2012-01-01T08:00:00.000Z","completed":true}},"vows":{"taoHelper":{"dateMade":"2012-11-04T07:00:00.000Z","made":true},"assistantLecturer":{"dateMade":"2013-09-22T07:00:00.000Z","made":true}},"currentTemple":"沾德壇"},{"id":1169,"birthDate":"1956-01-01T08:00:00.000Z","gender":"乾","age":66,"name":"劉志強","taoClasses":{"xingMing":{"completed":false},"zhiShan":{"completionDate":"2021-05-09T07:00:00.000Z","completed":true},"peiDe":{"completed":true,"completionDate":"2019-11-30T08:00:00.000Z"},"xingDe":{"completed":true,"completionDate":"2022-01-23T08:00:00.000Z"},"chongDe":{"completed":false},"lecturer":{"completed":false}},"currentTemple":"恆德壇","vows":{"taoHelper":{"made":true,"dateMade":"2019-05-12T07:00:00.000Z"}}},{"id":1213,"birthDate":"1963-01-01T08:00:00.000Z","gender":"坤","age":59,"name":"岑惠賢","taoClasses":{"lecturer":{"completed":false},"xingDe":{"completed":false},"peiDe":{"completionDate":"2019-11-30T08:00:00.000Z","completed":true},"zhiShan":{"completed":true,"completionDate":"2018-12-09T08:00:00.000Z"},"xingMing":{"completionDate":"2013-01-01T08:00:00.000Z","completed":true}},"vows":{"shareWealthAndTruth":{"made":true,"dateMade":"2018-11-11T08:00:00.000Z"},"holyOverWorldlyAffair":{"made":true,"dateMade":"2018-11-11T08:00:00.000Z"},"taoHelper":{"made":true,"dateMade":"2019-05-12T07:00:00.000Z"},"assistantLecturer":{"made":true,"dateMade":"2019-05-12T07:00:00.000Z"}},"currentTemple":"沾德壇"},{"id":1252,"birthDate":"1975-01-01T08:00:00.000Z","gender":"坤","age":47,"name":"梁敏儀","taoClasses":{"xingMing":{"completed":true,"completionDate":"2012-01-01T08:00:00.000Z"},"zhiShan":{"completed":true,"completionDate":"2022-01-23T08:00:00.000Z"},"peiDe":{"completed":false},"xingDe":{"completed":false},"chongDe":{"completed":false},"lecturer":{"completed":false}},"currentTemple":"恆德佛堂","vows":{"taoHelper":{"dateMade":"2018-05-13T07:00:00.000Z","made":true}}},{"id":1258,"birthDate":"1978-01-01T08:00:00.000Z","gender":"坤","age":44,"name":"朱麗芳","taoClasses":{"xingMing":{"completed":true,"completionDate":"2013-01-01T08:00:00.000Z"},"zhiShan":{"completed":true,"completionDate":"2018-12-09T08:00:00.000Z"},"peiDe":{"completed":true,"completionDate":"2019-11-30T08:00:00.000Z"},"xingDe":{"completed":true,"completionDate":"2021-05-09T07:00:00.000Z"},"chongDe":{"completed":true,"completionDate":"2022-01-23T08:00:00.000Z"},"lecturer":{"completed":false}},"currentTemple":"沾德壇","vows":{"taoHelper":{"dateMade":"2019-05-12T07:00:00.000Z","made":true},"assistantLecturer":{"dateMade":"2019-05-12T07:00:00.000Z","made":true}}},{"id":1394,"birthDate":"1982-01-01T08:00:00.000Z","gender":"坤","age":40,"name":"凌妹妹","taoClasses":{"xingMing":{"completed":true,"completionDate":"2018-12-09T08:00:00.000Z"},"zhiShan":{"completed":true,"completionDate":"2019-11-30T08:00:00.000Z"},"peiDe":{"completionDate":"2021-01-01T08:00:00.000Z","completed":true},"xingDe":{"completionDate":"2022-02-27T08:00:00.000Z","completed":true},"chongDe":{"completed":false},"lecturer":{"completed":false}},"currentTemple":"同德壇","vows":{"taoHelper":{"made":true,"dateMade":"2019-05-12T07:00:00.000Z"}}},{"id":1477,"birthDate":"1998-05-12T07:00:00.000Z","gender":"乾","age":24,"name":"Daniel Huynh","taoClasses":{"xingMing":{"completed":true,"completionDate":"2017-05-13T16:00:00.000Z"},"zhiShan":{"completed":false,"completionDate":"2018-05-13T07:00:00.000Z"},"peiDe":{"completed":false},"xingDe":{"completed":false},"chongDe":{"completed":false},"lecturer":{"completed":false}},"vows":{"holyOverWorldlyAffair":{"made":true,"dateMade":"2017-03-05T08:00:00.000Z"},"shareWealthAndTruth":{"made":true,"dateMade":"2017-03-05T08:00:00.000Z"},"taoHelper":{"made":true,"dateMade":"2017-05-13T07:00:00.000Z"}},"currentTemple":"同德壇"},{"id":1487,"birthDate":"2000-10-27T07:00:00.000Z","gender":"坤","age":22,"name":"Wendy Ly","altName":"李玟玟","taoClasses":{"lecturer":{"completed":false},"chongDe":{"completed":false},"xingDe":{"completed":false},"peiDe":{"completed":false},"zhiShan":{"completed":true,"completionDate":"2019-12-31T08:00:00.000Z"},"xingMing":{"completionDate":null,"completed":true}},"vows":{"taoHelper":{"made":true,"dateMade":"2019-05-12T07:00:00.000Z"},"shareWealthAndTruth":{"dateMade":"2018-08-19T08:00:00.000Z","made":true},"holyOverWorldlyAffair":{"dateMade":"2018-08-19T08:00:00.000Z","made":true}},"currentTemple":"恆德壇"},{"id":1496,"birthDate":"1936-01-01T08:00:00.000Z","currentTemple":"恆德壇","gender":"坤","age":86,"name":"林茉莉","taoClasses":{"chongDe":{"completionDate":"2019-11-30T08:00:00.000Z","completed":true},"lecturer":{"completed":false},"xingDe":{"completionDate":"2017-05-13T16:00:00.000Z","completed":true},"peiDe":{"completed":false},"zhiShan":{"completed":false},"xingMing":{"completed":false}},"vows":{"assistantLecturer":{"dateMade":"2016-06-12T07:00:00.000Z","made":true},"taoHelper":{"made":true,"dateMade":"2015-04-26T07:00:00.000Z"},"assistantTempleHost":{"dateMade":"2017-05-13T16:00:00.000Z","made":true},"templeHost":{},"lecturer":{},"transmittingMaster":{},"plantTaoSeed":{},"devoteToTaoPropagation":{},"establishTemple":{},"vegetarian":{},"shareWealthAndTruth":{},"holyOverWorldlyAffair":{}}},{"id":1502,"birthDate":"1955-01-01T08:00:00.000Z","currentTemple":"恆德佛堂","gender":"坤","age":67,"name":"周好儀","taoClasses":{"xingMing":{"completionDate":"2021-05-09T07:00:00.000Z","completed":true},"zhiShan":{"completed":true,"completionDate":"2022-01-23T08:00:00.000Z"},"peiDe":{"completed":false},"xingDe":{"completed":false},"lecturer":{"completed":false}}},{"id":1506,"birthDate":"1948-01-01T08:00:00.000Z","currentTemple":"恆德佛堂","gender":"坤","age":74,"name":"何幗賢","taoClasses":{"xingMing":{"completed":false},"zhiShan":{"completionDate":"2022-01-23T08:00:00.000Z","completed":true},"peiDe":{"completed":false},"xingDe":{"completed":false},"lecturer":{"completed":false}},"vows":{"holyOverWorldlyAffair":{"made":true,"dateMade":"2015-06-28T07:00:00.000Z"},"shareWealthAndTruth":{"made":true,"dateMade":"2015-06-28T07:00:00.000Z"},"taoHelper":{"made":true,"dateMade":"2018-05-13T07:00:00.000Z"}}},{"id":1512,"birthDate":"2002-02-05T08:00:00.000Z","currentTemple":"恆德佛堂","gender":"坤","age":20,"name":"Elly Su","taoClasses":{"xingMing":{"completed":true,"completionDate":"2018-12-09T08:00:00.000Z"},"zhiShan":{"completed":true,"completionDate":"2019-12-31T08:00:00.000Z"},"peiDe":{"completed":false},"xingDe":{"completed":false},"chongDe":{"completed":false},"lecturer":{"completed":false}},"vows":{"holyOverWorldlyAffair":{"made":true,"dateMade":"2018-08-19T08:00:00.000Z"},"shareWealthAndTruth":{"made":true,"dateMade":"2018-08-19T08:00:00.000Z"},"taoHelper":{"dateMade":"2019-05-12T07:00:00.000Z","made":true}},"altName":"粟愛麗"},{"id":1534,"birthDate":"1970-01-01T08:00:00.000Z","gender":"坤","age":52,"name":"莫影芬","taoClasses":{"xingMing":{"completed":false},"zhiShan":{"completed":true,"completionDate":"2017-05-13T16:00:00.000Z"},"peiDe":{"completed":false},"xingDe":{"completed":true,"completionDate":"2021-05-09T07:00:00.000Z"},"chongDe":{"completed":true,"completionDate":"2022-01-23T08:00:00.000Z"},"lecturer":{"completed":false}},"vows":{"vegetarian":{"dateMade":"2020-08-04T07:00:00.000Z","made":true},"assistantTempleHost":{"made":true},"taoHelper":{"made":true,"dateMade":"2015-04-26T07:00:00.000Z"}},"currentTemple":"沾德壇"},{"id":1607,"birthDate":"1963-01-01T08:00:00.000Z","gender":"乾","age":59,"name":"陳偉雄","taoClasses":{"lecturer":{"completed":false},"chongDe":{"completed":true,"completionDate":"2022-01-23T08:00:00.000Z"},"xingDe":{"completionDate":"2021-05-09T07:00:00.000Z","completed":true},"peiDe":{"completionDate":"2019-11-30T08:00:00.000Z","completed":true},"zhiShan":{"completionDate":"2018-12-09T08:00:00.000Z","completed":true},"xingMing":{"completed":false}},"vows":{"taoHelper":{"dateMade":null,"made":false},"assistantLecturer":{"made":true,"dateMade":"2019-05-12T07:00:00.000Z"}},"currentTemple":"恆德壇"},{"id":1805,"birthDate":"2004-01-20T08:00:00.000Z","currentTemple":"沾德壇","gender":"坤","age":18,"name":"Vivian Luong","taoClasses":{"xingMing":{"completed":true,"completionDate":"2022-04-30T07:00:00.000Z"},"zhiShan":{"completed":false},"peiDe":{"completed":false},"xingDe":{"completed":false},"chongDe":{"completed":false},"lecturer":{"completed":false}},"altName":"梁紫恩","vows":{"holyOverWorldlyAffair":{"made":true,"dateMade":"2021-08-22T07:00:00.000Z"},"shareWealthAndTruth":{"made":true,"dateMade":"2021-08-22T07:00:00.000Z"}}},{"id":1846,"birthDate":"2002-01-20T08:00:00.000Z","currentTemple":"沾德壇","gender":"乾","age":20,"name":"梁駿傑","taoClasses":{"xingMing":{"completionDate":"2022-04-30T07:00:00.000Z","completed":true},"zhiShan":{"completed":false},"peiDe":{"completed":false},"xingDe":{"completed":false},"chongDe":{"completed":false},"lecturer":{"completed":false}},"altName":"Winson Luong","vows":{"holyOverWorldlyAffair":{"dateMade":"2021-08-22T07:00:00.000Z","made":true},"shareWealthAndTruth":{"dateMade":"2021-08-22T07:00:00.000Z","made":true}}},{"id":1874,"birthDate":"1999-01-01T08:00:00.000Z","gender":"坤","age":23,"name":"Stella Yee","taoClasses":{"xingMing":{"completed":true,"completionDate":"2018-12-09T08:00:00.000Z"},"zhiShan":{"completed":true,"completionDate":"2019-12-31T08:00:00.000Z"},"peiDe":{"completed":false},"xingDe":{"completed":false},"chongDe":{"completed":false},"lecturer":{"completed":false}},"vows":{"holyOverWorldlyAffair":{"dateMade":"2017-03-05T08:00:00.000Z","made":true},"shareWealthAndTruth":{"dateMade":"2017-03-05T08:00:00.000Z","made":true},"taoHelper":{"made":true,"dateMade":"2019-05-12T07:00:00.000Z"}},"currentTemple":"沾德壇","altName":"余恩明"},{"id":1963,"currentTemple":"沾德壇","gender":"坤","name":"林萍","taoClasses":{"lecturer":{"completed":false},"xingDe":{"completed":false},"peiDe":{"completed":false},"zhiShan":{"completed":false},"xingMing":{"completionDate":"2022-01-23T08:00:00.000Z","completed":true}},"birthDate":"1964-01-01T00:00:00.000Z","age":59,"vows":{"holyOverWorldlyAffair":{"made":true,"dateMade":"2019-03-03T08:00:00.000Z"},"shareWealthAndTruth":{"made":true,"dateMade":"2019-03-03T08:00:00.000Z"}}},{"id":1974,"currentTemple":"恆德佛堂","gender":"坤","name":"何詠涵","altName":"Stacy Yong Han Hor","taoClasses":{"xingMing":{"completionDate":"2022-04-30T07:00:00.000Z","completed":true},"zhiShan":{"completed":false},"peiDe":{"completed":false},"xingDe":{"completed":false},"chongDe":{"completed":false},"lecturer":{"completed":false}},"birthDate":"2004-12-30T08:00:00.000Z","age":18,"vows":{"holyOverWorldlyAffair":{"made":true,"dateMade":"2021-08-22T07:00:00.000Z"},"shareWealthAndTruth":{"made":true,"dateMade":"2021-08-22T07:00:00.000Z"}}},{"id":2062,"birthDate":"2001-03-15T08:00:00.000Z","gender":"坤","age":21,"name":"Claire Cheang","taoClasses":{"xingMing":{"completed":true,"completionDate":"2018-12-09T08:00:00.000Z"},"zhiShan":{"completed":true,"completionDate":"2019-12-31T08:00:00.000Z"},"peiDe":{"completed":false},"xingDe":{"completed":false},"chongDe":{"completed":false},"lecturer":{"completed":false}},"altName":"鄭璇","vows":{"holyOverWorldlyAffair":{"dateMade":"2018-08-19T08:00:00.000Z","made":true},"shareWealthAndTruth":{"dateMade":"2018-08-19T08:00:00.000Z","made":true},"taoHelper":{"dateMade":"2019-05-12T07:00:00.000Z","made":true}},"currentTemple":"沾德壇"},{"id":2274,"birthDate":"1952-01-01T08:00:00.000Z","currentTemple":"沾德壇","gender":"坤","age":70,"name":"蘇桂英","taoClasses":{"lecturer":{"completed":false},"chongDe":{"completed":true,"completionDate":"2019-11-30T08:00:00.000Z"},"xingDe":{"completionDate":"2018-12-09T08:00:00.000Z","completed":true},"peiDe":{"completed":false},"zhiShan":{"completionDate":"2017-05-13T16:00:00.000Z","completed":true},"xingMing":{"completed":false}},"vows":{"taoHelper":{"dateMade":"2015-04-26T07:00:00.000Z","made":true},"vegetarian":{"dateMade":"2020-08-04T07:00:00.000Z","made":true},"assistantLecturer":{"made":true,"dateMade":"2017-05-13T16:00:00.000Z"},"assistantTempleHost":{"made":true,"dateMade":"2018-05-13T07:00:00.000Z"}}},{"id":2276,"birthDate":"1953-01-01T08:00:00.000Z","currentTemple":"儒德壇","gender":"坤","age":69,"name":"丁明仁","taoClasses":{"xingMing":{"completed":false},"zhiShan":{"completed":true,"completionDate":"2018-12-09T08:00:00.000Z"},"peiDe":{"completed":true,"completionDate":"2019-11-30T08:00:00.000Z"},"xingDe":{"completionDate":"2021-05-09T07:00:00.000Z","completed":true},"chongDe":{"completed":true,"completionDate":"2022-01-23T08:00:00.000Z"},"lecturer":{"completed":false}},"vows":{"vegetarian":{"dateMade":"2020-08-04T07:00:00.000Z","made":true},"taoHelper":{"dateMade":"2018-05-13T07:00:00.000Z","made":true},"assistantLecturer":{"dateMade":"2019-05-12T07:00:00.000Z","made":true}}},{"id":2339,"birthDate":"1964-01-01T08:00:00.000Z","gender":"坤","age":58,"name":"劉嘉蕙","taoClasses":{"xingMing":{"completed":true,"completionDate":"2016-06-12T07:00:00.000Z"},"zhiShan":{"completed":true,"completionDate":"2017-05-13T16:00:00.000Z"},"peiDe":{"completed":false},"xingDe":{"completed":true,"completionDate":"2018-12-09T08:00:00.000Z"},"chongDe":{"completed":true,"completionDate":"2019-11-30T08:00:00.000Z"},"lecturer":{"completed":false}},"vows":{"vegetarian":{"dateMade":"2020-08-04T07:00:00.000Z","made":true},"assistantTempleHost":{"dateMade":"2017-05-12T16:00:00.000Z","made":true},"taoHelper":{"dateMade":"2016-06-12T07:00:00.000Z","made":true},"assistantLecturer":{"made":true,"dateMade":"2017-05-13T16:00:00.000Z"}},"currentTemple":"沾德佛堂"},{"id":2395,"name":"廖文菁","taoClasses":{"lecturer":{"completed":false},"chongDe":{"completed":false},"xingDe":{"completed":false},"peiDe":{"completed":false},"zhiShan":{"completionDate":"2022-01-23T08:00:00.000Z","completed":true},"xingMing":{"completed":false}},"gender":"坤","currentTemple":"沾德壇","birthDate":"1976-01-01T08:00:00.000Z","age":46},{"name":"Cynthia Hsu","altName":"徐馨雅","gender":"坤","birthDate":"2003-02-25T08:00:00.000Z","id":2483,"taoClasses":{"xingMing":{"completed":true,"completionDate":"2021-06-19T07:00:00.000Z"},"zhiShan":{"completed":false},"peiDe":{"completed":false},"xingDe":{"completed":false},"chongDe":{"completed":false},"lecturer":{"completed":false}},"age":19,"vows":{"holyOverWorldlyAffair":{"dateMade":"2019-11-03T08:00:00.000Z","made":true},"shareWealthAndTruth":{"dateMade":"2019-11-03T08:00:00.000Z","made":true},"vegetarian":{"dateMade":"2020-08-04T07:00:00.000Z","made":true}},"currentTemple":"儒德壇"},{"name":"曾順興","gender":"乾","id":2484,"taoClasses":{"xingMing":{"completed":false},"zhiShan":{"completed":false},"peiDe":{"completed":false},"xingDe":{"completed":false},"lecturer":{"completed":false}},"birthDate":"1973-01-01T08:00:00.000Z","age":49,"vows":{"holyOverWorldlyAffair":{},"shareWealthAndTruth":{},"vegetarian":{"made":true},"establishTemple":{},"devoteToTaoPropagation":{},"plantTaoSeed":{},"transmittingMaster":{},"lecturer":{"made":true,"dateMade":"2017-05-13T16:00:00.000Z"},"templeHost":{"made":true,"dateMade":"2016-06-11T07:00:00.000Z"},"assistantTempleHost":{},"taoHelper":{},"assistantLecturer":{}},"currentTemple":"恆德壇","altName":"Sam Tseng"},{"name":"曾郁晴","gender":"坤","id":2486,"taoClasses":{"xingMing":{"completed":true,"completionDate":"2018-12-09T08:00:00.000Z"},"zhiShan":{"completed":true,"completionDate":"2019-12-31T08:00:00.000Z"},"peiDe":{"completed":false},"xingDe":{"completed":false},"chongDe":{"completed":false},"lecturer":{"completed":false}},"altName":"Ruby Tseng","birthDate":"2001-12-13T08:00:00.000Z","age":21,"vows":{"holyOverWorldlyAffair":{"made":true,"dateMade":"2018-08-19T08:00:00.000Z"},"shareWealthAndTruth":{"made":true,"dateMade":"2018-08-19T08:00:00.000Z"},"taoHelper":{"made":true,"dateMade":"2019-05-12T07:00:00.000Z"}},"currentTemple":"恆德壇"},{"name":"祝玉珍","gender":"坤","id":2489,"taoClasses":{"xingMing":{"completed":false},"zhiShan":{"completed":false},"peiDe":{"completed":false},"xingDe":{"completed":false},"chongDe":{"completed":false,"completionDate":null},"lecturer":{"completed":false}},"vows":{"holyOverWorldlyAffair":{"dateMade":"2008-10-25T07:00:00.000Z","made":true},"shareWealthAndTruth":{"made":true},"templeHost":{"made":false},"assistantTempleHost":{"dateMade":"2010-11-07T07:00:00.000Z","made":true},"taoHelper":{"made":true,"dateMade":"2008-10-25T07:00:00.000Z"},"assistantLecturer":{"dateMade":"2010-11-07T07:00:00.000Z","made":true}},"currentTemple":"聖德壇","altName":"Jane Chok"},{"name":"邱麗華","id":2495,"taoClasses":{"xingMing":{"completed":false},"zhiShan":{"completed":false},"peiDe":{"completed":false},"xingDe":{"completed":false},"lecturer":{"completed":false}},"gender":"坤"},{"name":"李晚霞","id":2536,"taoClasses":{"lecturer":{"completed":false},"xingDe":{"completed":false},"peiDe":{"completionDate":"2019-11-30T08:00:00.000Z","completed":true},"zhiShan":{"completed":true,"completionDate":"2018-12-09T08:00:00.000Z"},"xingMing":{"completed":false}},"gender":"坤","age":32,"currentTemple":"恆德佛堂","vows":{"taoHelper":{"dateMade":"2018-05-13T07:00:00.000Z","made":true},"shareWealthAndTruth":{"made":true,"dateMade":"2015-03-15T07:00:00.000Z"},"holyOverWorldlyAffair":{"made":true,"dateMade":"2015-03-15T07:00:00.000Z"},"assistantLecturer":{"made":true,"dateMade":"2019-05-12T07:00:00.000Z"}}},{"name":"李瑞金","id":2539,"taoClasses":{"chongDe":{"completionDate":"2019-11-30T08:00:00.000Z","completed":true},"lecturer":{"completed":false},"xingDe":{"completed":true,"completionDate":"2018-12-09T08:00:00.000Z"},"peiDe":{"completed":false},"zhiShan":{"completionDate":"2017-05-13T16:00:00.000Z","completed":true},"xingMing":{"completed":false}},"gender":"坤","vows":{"assistantLecturer":{"made":true,"dateMade":"2017-05-13T16:00:00.000Z"},"assistantTempleHost":{"made":true,"dateMade":"2018-05-13T07:00:00.000Z"},"vegetarian":{"made":true,"dateMade":"2019-05-12T07:00:00.000Z"},"templeHost":{"made":true,"dateMade":"2019-05-12T07:00:00.000Z"}},"currentTemple":"沾德壇"},{"name":"苗啟廣","age":16,"gender":"乾","currentTemple":"同德佛堂","id":2600,"taoClasses":{"xingMing":{"completed":true,"completionDate":"2017-05-13T16:00:00.000Z"},"zhiShan":{"completionDate":"2022-02-27T08:00:00.000Z","completed":true},"peiDe":{"completed":true,"completionDate":"2018-12-09T08:00:00.000Z"},"xingDe":{"completed":false},"chongDe":{"completed":false},"lecturer":{"completed":false}},"vows":{"holyOverWorldlyAffair":{"dateMade":"2015-06-28T07:00:00.000Z","made":true},"shareWealthAndTruth":{"dateMade":"2015-06-28T07:00:00.000Z","made":true},"taoHelper":{"dateMade":"2017-05-13T16:00:00.000Z","made":true}}},{"name":"苗啟煊","gender":"乾","age":23,"currentTemple":"同德佛堂","id":2601,"taoClasses":{"xingMing":{"completed":true,"completionDate":"2017-05-13T16:00:00.000Z"},"zhiShan":{"completionDate":"2022-02-27T08:00:00.000Z","completed":true},"peiDe":{"completed":false},"xingDe":{"completed":false},"chongDe":{"completed":false},"lecturer":{"completed":false}},"birthDate":"1999-01-01T08:00:00.000Z","vows":{"holyOverWorldlyAffair":{"made":true},"shareWealthAndTruth":{"made":true}}},{"name":"Trung Hoa Le","gender":"坤","id":2649,"taoClasses":{"xingMing":{"completed":true,"completionDate":"2017-05-13T16:00:00.000Z"},"zhiShan":{"completed":true,"completionDate":"2018-05-13T07:00:00.000Z"},"peiDe":{"completed":true,"completionDate":"2018-12-09T08:00:00.000Z"},"xingDe":{"completed":false},"chongDe":{"completed":false},"lecturer":{"completed":false}},"vows":{"holyOverWorldlyAffair":{"made":true},"shareWealthAndTruth":{"made":true},"taoHelper":{"made":true,"dateMade":"2017-05-13T16:00:00.000Z"}},"currentTemple":"同德壇"},{"name":"Harry Thiem Tieu","gender":"乾","age":63,"currentTemple":"同德壇","id":2692,"taoClasses":{"lecturer":{"completed":false},"xingDe":{"completed":true,"completionDate":"2013-01-01T08:00:00.000Z"},"peiDe":{"completed":true,"completionDate":"2012-01-01T08:00:00.000Z"},"zhiShan":{"completed":false},"xingMing":{"completed":false}},"vows":{"holyOverWorldlyAffair":{},"shareWealthAndTruth":{},"vegetarian":{"dateMade":"2015-04-26T07:00:00.000Z","made":true},"establishTemple":{},"devoteToTaoPropagation":{},"plantTaoSeed":{},"transmittingMaster":{"dateMade":null},"lecturer":{"dateMade":"2015-04-26T07:00:00.000Z","made":true},"templeHost":{"dateMade":"2011-11-06T07:00:00.000Z","made":true},"assistantTempleHost":{"dateMade":"2010-11-07T07:00:00.000Z","made":true},"taoHelper":{"dateMade":"2010-11-07T07:00:00.000Z","made":true},"assistantLecturer":{"made":true,"dateMade":"2011-11-06T07:00:00.000Z"}},"birthDate":"1959-01-01T08:00:00.000Z","altName":"蕭茂亮"},{"name":"邵金蓮","gender":"坤","age":74,"birthDate":"1948-01-01T08:00:00.000Z","currentTemple":"恆德佛堂","id":2701,"taoClasses":{"xingMing":{"completed":true,"completionDate":"2017-05-13T16:00:00.000Z"},"zhiShan":{"completionDate":"2018-12-09T08:00:00.000Z","completed":true},"peiDe":{"completionDate":"2019-11-30T08:00:00.000Z","completed":true},"xingDe":{"completed":false},"lecturer":{"completed":false}},"vows":{"holyOverWorldlyAffair":{"made":true},"shareWealthAndTruth":{"made":true},"taoHelper":{"dateMade":"2017-05-13T16:00:00.000Z","made":true},"assistantLecturer":{"made":true,"dateMade":"2019-05-12T07:00:00.000Z"}}},{"name":"鄭煒森","id":2704,"taoClasses":{"xingMing":{"completed":true,"completionDate":"2018-12-09T08:00:00.000Z"},"zhiShan":{"completionDate":"2019-12-31T08:00:00.000Z","completed":true},"peiDe":{"completed":false},"xingDe":{"completed":false},"chongDe":{"completed":false},"lecturer":{"completed":false}},"gender":"乾","currentTemple":"恆德佛堂","age":13,"vows":{"holyOverWorldlyAffair":{"dateMade":"2019-11-03T08:00:00.000Z","made":true},"shareWealthAndTruth":{"dateMade":"2019-11-03T08:00:00.000Z","made":true},"taoHelper":{"dateMade":"2019-05-12T07:00:00.000Z","made":true}},"altName":"Sam Zheng"},{"name":"劉威","gender":"坤","age":71,"birthDate":"1952-01-01T00:00:00.000Z","currentTemple":"同德佛堂","id":2820,"taoClasses":{"xingMing":{"completed":false},"zhiShan":{"completed":true,"completionDate":"2018-12-09T08:00:00.000Z"},"peiDe":{"completed":true,"completionDate":"2021-01-01T08:00:00.000Z"},"xingDe":{"completionDate":"2022-02-27T08:00:00.000Z","completed":true},"chongDe":{"completed":false},"lecturer":{"completed":false}}},{"name":"張玉梅","gender":"坤","age":68,"birthDate":"1954-01-01T08:00:00.000Z","currentTemple":"沾德壇","id":2857,"taoClasses":{"xingMing":{"completed":true,"completionDate":"2017-05-13T16:00:00.000Z"},"zhiShan":{"completed":false},"peiDe":{"completionDate":"2019-11-30T08:00:00.000Z","completed":true},"xingDe":{"completed":true,"completionDate":"2018-12-09T08:00:00.000Z"},"chongDe":{"completionDate":"2021-05-09T07:00:00.000Z","completed":true},"lecturer":{"completed":false}},"vows":{"assistantTempleHost":{"dateMade":"2018-05-13T07:00:00.000Z","made":true},"vegetarian":{"made":true,"dateMade":"2021-11-14T08:00:00.000Z"}}},{"name":"Isabel Wu","altName":"吳旻宸","gender":"坤","age":18,"id":2875,"taoClasses":{"xingMing":{"completed":true,"completionDate":"2022-04-30T07:00:00.000Z"},"zhiShan":{"completed":false},"peiDe":{"completed":false},"xingDe":{"completed":false},"chongDe":{"completed":false},"lecturer":{"completed":false}},"birthDate":"2004-08-24T07:00:00.000Z","vows":{"holyOverWorldlyAffair":{"made":true,"dateMade":"2021-08-22T07:00:00.000Z"},"shareWealthAndTruth":{"made":true,"dateMade":"2021-08-22T07:00:00.000Z"}},"currentTemple":"恆德壇"},{"name":"連千慧","gender":"坤","currentTemple":"沾德壇","id":2956,"taoClasses":{"xingMing":{"completed":true,"completionDate":"2017-05-13T16:00:00.000Z"},"zhiShan":{"completed":true,"completionDate":"2022-01-23T08:00:00.000Z"},"peiDe":{"completed":true,"completionDate":"2021-01-01T08:00:00.000Z"},"xingDe":{"completed":false},"chongDe":{"completed":false},"lecturer":{"completed":false}},"vows":{"vegetarian":{"made":true,"dateMade":"2021-03-09T08:00:00.000Z"}}},{"name":"伍心成","id":3022,"taoClasses":{"lecturer":{"completed":false},"xingDe":{"completionDate":"2021-05-09T07:00:00.000Z","completed":true},"peiDe":{"completionDate":"2019-11-30T08:00:00.000Z","completed":true},"zhiShan":{"completed":true,"completionDate":"2018-12-09T08:00:00.000Z"},"xingMing":{"completed":false},"chongDe":{"completed":true,"completionDate":"2022-01-23T08:00:00.000Z"}},"currentTemple":"沾德壇","birthDate":"1989-01-01T08:00:00.000Z","age":33,"gender":"乾","vows":{"taoHelper":{"dateMade":"2018-05-13T07:00:00.000Z","made":true},"assistantLecturer":{"made":true,"dateMade":"2019-05-12T07:00:00.000Z"}}},{"name":"姜海棠","gender":"坤","age":72,"birthDate":"1950-03-17T07:00:00.000Z","id":3025,"taoClasses":{"xingMing":{"completed":false},"zhiShan":{"completed":true,"completionDate":"2018-12-09T08:00:00.000Z"},"peiDe":{"completed":true,"completionDate":"2019-11-30T08:00:00.000Z"},"xingDe":{"completionDate":"2022-02-27T08:00:00.000Z","completed":true},"chongDe":{"completed":false},"lecturer":{"completed":false}},"currentTemple":"同德佛堂","vows":{"holyOverWorldlyAffair":{"made":true,"dateMade":"2017-03-05T08:00:00.000Z"},"shareWealthAndTruth":{"made":true,"dateMade":"2017-03-05T08:00:00.000Z"},"vegetarian":{"dateMade":"2020-08-04T07:00:00.000Z","made":true},"taoHelper":{"dateMade":"2018-05-13T07:00:00.000Z","made":true},"assistantLecturer":{"made":true,"dateMade":"2019-05-12T07:00:00.000Z"}}},{"name":"鄭琪睿","gender":"坤","age":18,"birthDate":"2004-04-02T08:00:00.000Z","currentTemple":"恆德佛堂","id":3053,"taoClasses":{"xingMing":{"completionDate":"2022-04-30T07:00:00.000Z","completed":true},"zhiShan":{"completed":false},"peiDe":{"completed":false},"xingDe":{"completed":false},"chongDe":{"completed":false},"lecturer":{"completed":false}},"altName":"Qirui (Sara) Zheng","vows":{"holyOverWorldlyAffair":{"made":true,"dateMade":"2021-08-22T07:00:00.000Z"},"shareWealthAndTruth":{"made":true,"dateMade":"2021-08-22T07:00:00.000Z"}}},{"name":"林育賢","gender":"乾","id":3068,"taoClasses":{"xingMing":{"completed":false},"zhiShan":{"completed":false},"peiDe":{"completed":false},"xingDe":{"completed":true,"completionDate":"2018-12-09T08:00:00.000Z"},"chongDe":{"completed":true,"completionDate":"2019-11-30T08:00:00.000Z"},"lecturer":{"completed":false}},"vows":{"vegetarian":{"made":true,"dateMade":"2018-05-13T07:00:00.000Z"},"templeHost":{"made":true,"dateMade":"2019-05-12T07:00:00.000Z"}},"currentTemple":"沾德壇","altName":"Yu Xian Lim"},{"name":"Michael Fenech","gender":"乾","age":52,"birthDate":"1970-01-01T08:00:00.000Z","currentTemple":"沾德壇","id":3085,"taoClasses":{"xingMing":{"completed":true},"zhiShan":{"completionDate":"2018-12-09T08:00:00.000Z","completed":true},"peiDe":{"completionDate":"2019-11-30T08:00:00.000Z","completed":true},"xingDe":{"completionDate":"2021-05-09T07:00:00.000Z","completed":true},"lecturer":{"completed":false},"chongDe":{"completed":true,"completionDate":"2022-01-23T08:00:00.000Z"}},"vows":{"templeHost":{"dateMade":"2019-05-12T07:00:00.000Z","made":true},"assistantLecturer":{"dateMade":"2019-05-12T07:00:00.000Z","made":true},"holyOverWorldlyAffair":{"dateMade":"2017-03-05T08:00:00.000Z","made":true},"shareWealthAndTruth":{"dateMade":"2017-03-05T08:00:00.000Z","made":true},"vegetarian":{"made":true,"dateMade":"2018-11-11T08:00:00.000Z"},"taoHelper":{"made":true,"dateMade":"2018-05-13T07:00:00.000Z"}}},{"name":"黃清俊","gender":"乾","id":3089,"taoClasses":{"lecturer":{"completed":false},"chongDe":{"completed":true,"completionDate":"2022-01-23T08:00:00.000Z"},"xingDe":{"completionDate":"2021-05-09T07:00:00.000Z","completed":true},"peiDe":{"completionDate":"2019-11-30T08:00:00.000Z","completed":true},"zhiShan":{"completionDate":"2018-12-09T08:00:00.000Z","completed":true},"xingMing":{"completed":false}},"currentTemple":"沾德壇","vows":{"assistantLecturer":{"dateMade":"2019-05-12T07:00:00.000Z","made":true},"taoHelper":{"dateMade":"2018-05-13T07:00:00.000Z","made":true},"templeHost":{"made":true,"dateMade":"2018-05-13T07:00:00.000Z"},"vegetarian":{"dateMade":"2018-05-13T07:00:00.000Z","made":true}}},{"name":"陳金春","gender":"坤","id":3090,"taoClasses":{"xingMing":{"completed":false},"zhiShan":{"completed":true,"completionDate":"2018-12-09T08:00:00.000Z"},"peiDe":{"completionDate":"2019-11-30T08:00:00.000Z","completed":true},"xingDe":{"completionDate":"2021-05-09T07:00:00.000Z","completed":true},"chongDe":{"completed":true,"completionDate":"2022-01-23T08:00:00.000Z"},"lecturer":{"completed":false}},"currentTemple":"沾德壇","vows":{"vegetarian":{"dateMade":"2018-05-13T07:00:00.000Z","made":true},"taoHelper":{"dateMade":"2018-05-13T07:00:00.000Z","made":true},"templeHost":{"dateMade":"2018-05-13T07:00:00.000Z","made":true},"assistantLecturer":{"made":true,"dateMade":"2019-05-12T07:00:00.000Z"}}},{"gender":"坤","name":"Lynne Chau","altName":"周姐","age":60,"birthDate":"1962-05-07T07:00:00.000Z","currentTemple":"同德佛堂","id":3110,"taoClasses":{"xingMing":{"completed":true,"completionDate":"2018-12-09T08:00:00.000Z"},"zhiShan":{"completed":true,"completionDate":"2019-11-30T08:00:00.000Z"},"peiDe":{"completionDate":"2021-01-01T08:00:00.000Z","completed":true},"xingDe":{"completionDate":"2022-02-27T08:00:00.000Z","completed":true},"chongDe":{"completed":false},"lecturer":{"completed":false}},"vows":{"holyOverWorldlyAffair":{"dateMade":"2017-06-11T07:00:00.000Z","made":true},"shareWealthAndTruth":{"dateMade":"2017-06-11T07:00:00.000Z","made":true},"taoHelper":{"dateMade":"2019-05-12T07:00:00.000Z","made":true}}},{"name":"鄭南保","id":3119,"taoClasses":{"xingMing":{"completionDate":"2021-05-09T07:00:00.000Z","completed":true},"zhiShan":{"completed":true,"completionDate":"2022-01-23T08:00:00.000Z"},"peiDe":{"completed":false},"xingDe":{"completed":false},"lecturer":{"completed":false}},"currentTemple":"恆德佛堂","birthDate":"1976-01-01T08:00:00.000Z","age":46,"gender":"乾"},{"name":"王養志","gender":"乾","age":63,"birthDate":"1959-01-01T08:00:00.000Z","currentTemple":"沾德佛堂","id":3132,"taoClasses":{"xingMing":{"completionDate":"2021-05-09T07:00:00.000Z","completed":true},"zhiShan":{"completed":true,"completionDate":"2022-01-23T08:00:00.000Z"},"peiDe":{"completed":false},"xingDe":{"completed":false},"lecturer":{"completed":false}},"vows":{"shareWealthAndTruth":{"made":true},"holyOverWorldlyAffair":{"made":true}}},{"name":"Anna Tran","altName":"陳文文","gender":"坤","id":3147,"taoClasses":{"xingMing":{"completed":true,"completionDate":"2018-12-09T08:00:00.000Z"},"zhiShan":{"completionDate":"2019-12-31T08:00:00.000Z","completed":true},"peiDe":{"completed":false},"xingDe":{"completed":false},"chongDe":{"completed":false},"lecturer":{"completed":false}},"age":22,"birthDate":"2000-01-01T08:00:00.000Z","vows":{"holyOverWorldlyAffair":{"made":true,"dateMade":"2018-08-19T08:00:00.000Z"},"shareWealthAndTruth":{"made":true,"dateMade":"2018-08-19T08:00:00.000Z"},"taoHelper":{"made":true,"dateMade":"2019-05-12T07:00:00.000Z"}},"currentTemple":"沾德壇"},{"name":"江金鳳","gender":"坤","currentTemple":"沾德壇","id":3183,"vows":{"holyOverWorldlyAffair":{},"shareWealthAndTruth":{},"vegetarian":{"dateMade":"2022-03-27T07:00:00.000Z","made":true},"establishTemple":{},"devoteToTaoPropagation":{},"plantTaoSeed":{},"transmittingMaster":{},"lecturer":{},"templeHost":{},"assistantTempleHost":{"dateMade":"2017-05-13T16:00:00.000Z","made":true},"taoHelper":{"made":true,"dateMade":"2003-08-20T07:00:00.000Z"},"assistantLecturer":{}},"taoClasses":{"xingMing":{"completed":false},"zhiShan":{"completed":false},"peiDe":{"completed":true,"completionDate":"2021-05-09T07:00:00.000Z"},"xingDe":{"completionDate":"2022-01-23T08:00:00.000Z","completed":true},"lecturer":{"completed":false}}},{"name":"牛湘君","gender":"坤","age":73,"birthDate":"1949-01-01T08:00:00.000Z","currentTemple":"同德佛堂","id":3526,"taoClasses":{"xingMing":{"completed":true,"completionDate":"2018-12-09T08:00:00.000Z"},"zhiShan":{"completed":true,"completionDate":"2019-11-30T08:00:00.000Z"},"peiDe":{"completed":true,"completionDate":"2021-01-01T08:00:00.000Z"},"xingDe":{"completionDate":"2022-02-27T08:00:00.000Z","completed":true},"chongDe":{"completed":false},"lecturer":{"completed":false}},"vows":{"holyOverWorldlyAffair":{"dateMade":"2018-03-04T08:00:00.000Z","made":true},"shareWealthAndTruth":{"dateMade":"2018-03-04T08:00:00.000Z","made":true},"taoHelper":{"made":true,"dateMade":"2019-05-12T07:00:00.000Z"}}},{"name":"朱院丹","gender":"坤","age":67,"birthDate":"1955-01-01T08:00:00.000Z","currentTemple":"恆德佛堂","id":3528,"taoClasses":{"lecturer":{"completed":false},"xingDe":{"completed":false},"peiDe":{"completed":false},"zhiShan":{"completed":true,"completionDate":"2022-01-23T08:00:00.000Z"},"xingMing":{"completionDate":"2021-05-09T07:00:00.000Z","completed":true}},"vows":{"holyOverWorldlyAffair":{"made":true,"dateMade":"2018-03-04T08:00:00.000Z"},"shareWealthAndTruth":{"made":true,"dateMade":"2018-03-04T08:00:00.000Z"}}},{"name":"伍惠卿","id":3660,"taoClasses":{"lecturer":{"completed":false},"xingDe":{"completed":false},"peiDe":{"completed":false},"zhiShan":{"completed":true,"completionDate":"2022-01-23T08:00:00.000Z"},"xingMing":{"completionDate":"2021-05-09T07:00:00.000Z","completed":true}},"currentTemple":"恆德佛堂","birthDate":"1961-01-01T08:00:00.000Z","age":61,"gender":"坤","vows":{"shareWealthAndTruth":{"dateMade":"2021-08-15T07:00:00.000Z","made":true},"holyOverWorldlyAffair":{"dateMade":"2021-08-15T07:00:00.000Z","made":true}}},{"name":"官曉文","altName":"Xiaowen Guan","gender":"坤","id":3667,"taoClasses":{"lecturer":{"completed":false},"chongDe":{"completionDate":"2019-11-30T08:00:00.000Z","completed":true},"xingDe":{"completed":false},"peiDe":{"completed":false},"zhiShan":{"completed":false},"xingMing":{"completed":false}},"currentTemple":"沾德壇","vows":{"assistantTempleHost":{"dateMade":"2019-05-12T07:00:00.000Z","made":true}}},{"id":3717,"taoClasses":{"lecturer":{"completed":false},"xingDe":{"completed":false},"peiDe":{"completed":false},"zhiShan":{"completionDate":null,"completed":false},"xingMing":{"completed":true,"completionDate":"2019-11-30T08:00:00.000Z"}},"name":"林玉梅","currentTemple":"恆德佛堂","birthDate":"1962-01-01T08:00:00.000Z","age":60,"gender":"坤","vows":{"shareWealthAndTruth":{"dateMade":"2018-11-11T08:00:00.000Z","made":true},"holyOverWorldlyAffair":{"dateMade":"2018-11-11T08:00:00.000Z","made":true}}},{"name":"許阿霞","gender":"坤","birthDate":"1940-07-21T08:00:00.000Z","age":82,"id":3741,"taoClasses":{"xingMing":{"completed":true,"completionDate":"2018-12-09T08:00:00.000Z"},"zhiShan":{"completed":true,"completionDate":"2019-11-30T08:00:00.000Z"},"peiDe":{"completionDate":"2021-01-01T08:00:00.000Z","completed":true},"xingDe":{"completionDate":"2022-02-27T08:00:00.000Z","completed":true},"chongDe":{"completed":false},"lecturer":{"completed":false}},"currentTemple":"同德壇"},{"name":"莊孟蒔","gender":"乾","age":33,"birthDate":"1989-01-01T08:00:00.000Z","currentTemple":"正德壇","id":3750,"taoClasses":{"xingMing":{"completionDate":"2019-11-30T08:00:00.000Z","completed":true},"zhiShan":{"completionDate":"2021-05-09T07:00:00.000Z","completed":true},"peiDe":{"completed":true,"completionDate":"2022-01-23T08:00:00.000Z"},"xingDe":{"completed":false},"lecturer":{"completed":false}},"vows":{"shareWealthAndTruth":{"dateMade":"2019-03-03T08:00:00.000Z","made":true},"holyOverWorldlyAffair":{"dateMade":"2019-03-03T08:00:00.000Z","made":true}}},{"name":"岑如珠","id":3815,"taoClasses":{"lecturer":{"completed":false},"chongDe":{"completed":false},"xingDe":{"completed":false},"peiDe":{"completed":true,"completionDate":"2022-01-23T08:00:00.000Z"},"zhiShan":{"completionDate":"2021-05-09T07:00:00.000Z","completed":true},"xingMing":{"completionDate":"2019-11-30T08:00:00.000Z","completed":true}},"currentTemple":"恆德佛堂","birthDate":"1967-01-01T08:00:00.000Z","age":55,"gender":"坤","vows":{"shareWealthAndTruth":{"dateMade":"2019-07-28T08:00:00.000Z","made":true},"holyOverWorldlyAffair":{"dateMade":"2019-07-28T08:00:00.000Z","made":true}}},{"name":"李本華","gender":"乾","age":35,"birthDate":"1987-07-16T07:00:00.000Z","currentTemple":"正德佛堂","id":3835,"taoClasses":{"xingMing":{"completionDate":"2019-11-30T08:00:00.000Z","completed":true},"zhiShan":{"completionDate":"2021-05-09T07:00:00.000Z","completed":true},"peiDe":{"completed":true,"completionDate":"2022-01-23T08:00:00.000Z"},"xingDe":{"completed":false},"chongDe":{"completed":false},"lecturer":{"completed":false}},"vows":{"shareWealthAndTruth":{"dateMade":"2019-07-28T08:00:00.000Z","made":true},"holyOverWorldlyAffair":{"dateMade":"2019-07-28T08:00:00.000Z","made":true}}},{"name":"U SOE LI","gender":"乾","age":59,"birthDate":"1963-10-10T07:00:00.000Z","id":3849,"taoClasses":{"xingMing":{"completed":true,"completionDate":"2019-11-30T08:00:00.000Z"},"zhiShan":{"completionDate":"2021-05-09T07:00:00.000Z","completed":true},"peiDe":{"completionDate":"2022-01-23T08:00:00.000Z","completed":true},"xingDe":{"completed":false},"chongDe":{"completed":false},"lecturer":{"completed":false}},"currentTemple":"沾德佛堂","altName":"楊冕清","vows":{"holyOverWorldlyAffair":{"made":true,"dateMade":"2019-07-28T08:00:00.000Z"},"shareWealthAndTruth":{"made":true,"dateMade":"2019-07-28T08:00:00.000Z"}}},{"name":"廖雪明","gender":"坤","birthDate":"1961-01-01T08:00:00.000Z","age":61,"currentTemple":"同德佛堂","id":3860,"taoClasses":{"xingMing":{"completionDate":"2021-01-01T08:00:00.000Z","completed":true},"zhiShan":{"completed":false},"peiDe":{"completed":false},"xingDe":{"completed":false},"chongDe":{"completed":false},"lecturer":{"completed":false}},"vows":{"holyOverWorldlyAffair":{"dateMade":"2019-07-28T08:00:00.000Z","made":true},"shareWealthAndTruth":{"dateMade":"2019-07-28T08:00:00.000Z","made":true}}},{"name":"郭雨","gender":"坤","age":31,"birthDate":"1991-01-01T08:00:00.000Z","currentTemple":"沾德佛堂","id":3867,"taoClasses":{"lecturer":{"completed":false},"chongDe":{"completed":false},"xingDe":{"completed":false},"peiDe":{"completed":false},"zhiShan":{"completed":false},"xingMing":{"completionDate":"2021-01-01T08:00:00.000Z","completed":true}},"vows":{"shareWealthAndTruth":{"dateMade":"2019-07-28T08:00:00.000Z","made":true},"holyOverWorldlyAffair":{"dateMade":"2019-07-28T08:00:00.000Z","made":true}}},{"name":"吳彩群","gender":"坤","age":33,"birthDate":"1989-07-01T07:00:00.000Z","currentTemple":"明德壇","id":3904,"taoClasses":{"lecturer":{"completed":false},"chongDe":{"completed":false},"xingDe":{"completed":false},"peiDe":{"completed":false},"zhiShan":{"completed":false},"xingMing":{"completionDate":"2021-05-09T07:00:00.000Z","completed":true}},"vows":{"shareWealthAndTruth":{"dateMade":"2021-11-14T08:00:00.000Z","made":true},"holyOverWorldlyAffair":{"made":true,"dateMade":"2021-11-14T08:00:00.000Z"}}},{"name":"梅曼娜","gender":"坤","age":49,"birthDate":"1973-01-01T08:00:00.000Z","currentTemple":"沾德佛堂","id":3937,"taoClasses":{"xingMing":{"completionDate":"2019-11-30T08:00:00.000Z","completed":true},"zhiShan":{"completed":true,"completionDate":"2021-05-09T07:00:00.000Z"},"peiDe":{"completionDate":"2022-01-23T08:00:00.000Z","completed":true},"xingDe":{"completed":false},"chongDe":{"completed":false},"lecturer":{"completed":false}},"vows":{"shareWealthAndTruth":{"dateMade":"2019-07-28T08:00:00.000Z","made":true},"holyOverWorldlyAffair":{"dateMade":"2019-07-28T08:00:00.000Z","made":true},"vegetarian":{"made":true,"dateMade":"2021-04-26T07:00:00.000Z"}}},{"name":"劉煥棠","gender":"乾","age":80,"birthDate":"1942-01-01T08:00:00.000Z","currentTemple":"明德壇","id":3956,"taoClasses":{"lecturer":{"completed":false},"chongDe":{"completed":false},"xingDe":{"completed":false},"peiDe":{"completed":true,"completionDate":"2022-01-23T08:00:00.000Z"},"zhiShan":{"completionDate":"2021-05-09T07:00:00.000Z","completed":true},"xingMing":{"completed":false}},"vows":{"holyOverWorldlyAffair":{"made":true,"dateMade":"2019-11-03T08:00:00.000Z"},"shareWealthAndTruth":{"made":true,"dateMade":"2019-11-03T08:00:00.000Z"}}},{"name":"陳培基","gender":"乾","age":84,"birthDate":"1938-01-01T08:00:00.000Z","currentTemple":"同德佛堂","id":3981,"taoClasses":{"xingMing":{"completionDate":"2021-01-01T08:00:00.000Z","completed":true},"zhiShan":{"completionDate":"2022-02-27T08:00:00.000Z","completed":true},"peiDe":{"completed":false},"xingDe":{"completed":false},"chongDe":{"completed":false},"lecturer":{"completed":false}}},{"name":"楊偉英","gender":"坤","age":55,"currentTemple":"正德壇","id":4021,"taoClasses":{"lecturer":{"completed":false},"chongDe":{"completed":false},"xingDe":{"completed":false},"peiDe":{"completed":false},"zhiShan":{"completed":true,"completionDate":"2022-01-23T08:00:00.000Z"},"xingMing":{"completionDate":"2021-05-09T07:00:00.000Z","completed":true}},"vows":{"holyOverWorldlyAffair":{"made":true,"dateMade":"2019-11-03T08:00:00.000Z"},"shareWealthAndTruth":{"made":true,"dateMade":"2019-11-03T08:00:00.000Z"}}},{"name":"李桂芬","gender":"坤","age":42,"birthDate":"1981-01-01T00:00:00.000Z","altName":"HSUCH","currentTemple":"沾德壇","id":4047,"taoClasses":{"lecturer":{"completed":false},"chongDe":{"completed":false},"xingDe":{"completed":false},"peiDe":{"completed":false},"zhiShan":{"completionDate":"2022-01-23T08:00:00.000Z","completed":true},"xingMing":{"completionDate":"2021-05-09T07:00:00.000Z","completed":true}},"vows":{"shareWealthAndTruth":{"dateMade":"2021-07-18T07:00:00.000Z","made":true},"holyOverWorldlyAffair":{"dateMade":"2021-07-18T07:00:00.000Z","made":true}}},{"name":"Kaung Khant Hein Yang","altName":"楊世任","gender":"乾","birthDate":"1996-01-01T08:00:00.000Z","age":26,"currentTemple":"沾德佛堂","id":4083,"taoClasses":{"lecturer":{"completed":false},"chongDe":{"completed":false},"xingDe":{"completed":false},"peiDe":{"completed":false},"zhiShan":{"completed":false},"xingMing":{"completionDate":"2022-01-23T08:00:00.000Z","completed":true}},"vows":{"shareWealthAndTruth":{"dateMade":"2021-07-18T07:00:00.000Z","made":true},"holyOverWorldlyAffair":{"dateMade":"2021-07-18T07:00:00.000Z","made":true}}},{"name":"周靜月","gender":"坤","age":47,"birthDate":"1975-01-01T08:00:00.000Z","currentTemple":"沾德佛堂","id":4084,"taoClasses":{"lecturer":{"completed":false},"chongDe":{"completed":false},"xingDe":{"completed":false},"peiDe":{"completed":false},"zhiShan":{"completed":true,"completionDate":"2022-01-23T08:00:00.000Z"},"xingMing":{"completionDate":"2021-05-09T07:00:00.000Z","completed":true}},"vows":{"holyOverWorldlyAffair":{"made":true,"dateMade":"2021-07-18T07:00:00.000Z"},"shareWealthAndTruth":{"made":true,"dateMade":"2021-07-18T07:00:00.000Z"}}},{"name":"鄧筱","gender":"坤","age":72,"birthDate":"1950-01-01T08:00:00.000Z","currentTemple":"沾德壇","id":4092,"taoClasses":{"lecturer":{"completed":false},"chongDe":{"completed":false},"xingDe":{"completed":false},"peiDe":{"completed":false},"zhiShan":{"completed":true,"completionDate":"2022-01-23T08:00:00.000Z"},"xingMing":{"completionDate":"2021-05-09T07:00:00.000Z","completed":true}},"vows":{"shareWealthAndTruth":{"dateMade":"2021-08-15T07:00:00.000Z","made":true},"holyOverWorldlyAffair":{"dateMade":"2021-08-15T07:00:00.000Z","made":true}}},{"name":"張寶玓","gender":"乾","age":66,"birthDate":"1956-01-01T08:00:00.000Z","currentTemple":"沾德佛堂","id":4112,"taoClasses":{"xingMing":{"completed":true,"completionDate":"2021-05-09T07:00:00.000Z"},"zhiShan":{"completionDate":"2022-01-23T08:00:00.000Z","completed":true},"peiDe":{"completed":false},"xingDe":{"completed":false},"chongDe":{"completed":false},"lecturer":{"completed":false}},"vows":{"holyOverWorldlyAffair":{"dateMade":"2021-11-14T08:00:00.000Z","made":true},"shareWealthAndTruth":{"dateMade":"2021-11-14T08:00:00.000Z","made":true}}},{"name":"余穎","gender":"坤","age":40,"birthDate":"1982-01-01T08:00:00.000Z","currentTemple":"恆德佛堂","id":4139,"taoClasses":{"lecturer":{"completed":false},"chongDe":{"completed":false},"xingDe":{"completed":false},"peiDe":{"completed":false},"zhiShan":{"completed":false},"xingMing":{"completionDate":"2022-01-23T08:00:00.000Z","completed":true}}},{"name":"邱海霞","gender":"坤","age":27,"birthDate":"1995-01-01T08:00:00.000Z","currentTemple":"儒德壇","id":4140,"taoClasses":{"lecturer":{"completed":false},"chongDe":{"completed":false},"xingDe":{"completed":false},"peiDe":{"completed":false},"zhiShan":{"completed":false},"xingMing":{"completionDate":"2022-01-23T08:00:00.000Z","completed":true}},"vows":{"shareWealthAndTruth":{"dateMade":"2021-11-14T08:00:00.000Z","made":true},"holyOverWorldlyAffair":{"dateMade":"2021-11-14T08:00:00.000Z","made":true}}},{"name":"李裕英","gender":"坤","age":42,"birthDate":"1980-11-13T08:00:00.000Z","currentTemple":"恆德佛堂","id":4142,"taoClasses":{"lecturer":{"completed":false},"chongDe":{"completed":false},"xingDe":{"completed":false},"peiDe":{"completed":false},"zhiShan":{"completed":true,"completionDate":"2022-01-23T08:00:00.000Z"},"xingMing":{"completed":true,"completionDate":"2021-05-09T07:00:00.000Z"}},"vows":{"shareWealthAndTruth":{"dateMade":"2021-08-15T07:00:00.000Z","made":true},"holyOverWorldlyAffair":{"dateMade":"2021-08-15T07:00:00.000Z","made":true}}},{"name":"方杰曄","id":4168,"taoClasses":{"xingMing":{"completionDate":"2021-06-19T07:00:00.000Z","completed":true},"zhiShan":{"completed":false},"peiDe":{"completed":false},"xingDe":{"completed":false},"chongDe":{"completed":false},"lecturer":{"completed":false}},"currentTemple":"儒德壇","age":20,"gender":"坤","vows":{"holyOverWorldlyAffair":{"made":true,"dateMade":"2021-07-18T07:00:00.000Z"},"shareWealthAndTruth":{"made":true,"dateMade":"2021-07-18T07:00:00.000Z"}},"altName":"Jieye Fang"},{"name":"陳玉蘭","gender":"坤","age":52,"birthDate":"1970-01-22T08:00:00.000Z","currentTemple":"正德佛堂","id":4260,"taoClasses":{"xingMing":{"completionDate":"2022-01-23T08:00:00.000Z","completed":true},"zhiShan":{"completed":false},"peiDe":{"completed":false},"xingDe":{"completed":false},"chongDe":{"completed":false},"lecturer":{"completed":false}},"vows":{"shareWealthAndTruth":{"dateMade":"2021-07-25T07:00:00.000Z","made":true},"holyOverWorldlyAffair":{"dateMade":"2021-07-25T07:00:00.000Z","made":true}}},{"name":"梁華安","id":4264,"taoClasses":{"xingMing":{"completionDate":"2021-05-09T07:00:00.000Z","completed":true},"zhiShan":{"completed":true,"completionDate":"2022-01-23T08:00:00.000Z"},"peiDe":{"completed":false},"xingDe":{"completed":false},"chongDe":{"completed":false},"lecturer":{"completed":false}},"currentTemple":"明德壇","birthDate":"1964-01-01T08:00:00.000Z","age":58,"gender":"乾"},{"name":"李潔","gender":"坤","birthDate":"1972-01-01T08:00:00.000Z","age":50,"currentTemple":"沾德壇","id":4293,"taoClasses":{"lecturer":{"completed":false},"chongDe":{"completed":false},"xingDe":{"completed":false},"peiDe":{"completed":false},"zhiShan":{"completed":false},"xingMing":{"completionDate":"2022-01-23T08:00:00.000Z","completed":true}},"vows":{"shareWealthAndTruth":{"dateMade":"2021-11-14T08:00:00.000Z","made":true},"holyOverWorldlyAffair":{"dateMade":"2021-11-14T08:00:00.000Z","made":true}}},{"name":"王小魚","altName":"Patrick Wang","gender":"乾","age":46,"birthDate":"1976-01-01T08:00:00.000Z","currentTemple":"同德佛堂","id":4375,"taoClasses":{"xingMing":{"completionDate":"2022-02-27T08:00:00.000Z","completed":true},"zhiShan":{"completed":false},"peiDe":{"completed":false},"xingDe":{"completed":false},"chongDe":{"completed":false},"lecturer":{"completed":false}}},{"name":"周碧流","gender":"坤","currentTemple":"聖德壇","id":4520,"taoClasses":{"xingMing":{"completed":true,"completionDate":"2022-02-27T08:00:00.000Z"},"zhiShan":{"completed":false},"peiDe":{"completed":false},"xingDe":{"completed":false},"chongDe":{"completed":false},"lecturer":{"completed":false}},"altName":"Julia Zhou"}]